better_fsm/__init__.py
better_fsm/context.py
better_fsm/middlewares.py
better_fsm/mixins.py
better_fsm/py.typed
better_fsm/data/__init__.py
better_fsm/data/constants.py
better_fsm/data/exceptions.py
better_fsm/data/manager.py
better_fsm/states/__init__.py
better_fsm/states/group.py
better_fsm/states/manager.py
better_fsm/states/state.py
better_fsm/utils/__init__.py
better_fsm/utils/attrs.py
better_fsm/utils/func.py
better_fsm-0.0.9.dist-info/METADATA
better_fsm-0.0.9.dist-info/WHEEL
better_fsm-0.0.9.dist-info/top_level.txt
better_fsm-0.0.9.dist-info/RECORD
