Metadata-Version: 2.1
Name: better-fsm
Version: 0.0.9
Requires-Dist: aiogram (>=3.0.0b7)
